lastfm/__init__.py
lastfm/charts.py
lastfm/search.py
lastfm/fmtypes/__init__.py
lastfm/fmtypes/fmtypes.py
lastfmapi_py-1.0.0.dist-info/LICENSE
lastfmapi_py-1.0.0.dist-info/METADATA
lastfmapi_py-1.0.0.dist-info/WHEEL
lastfmapi_py-1.0.0.dist-info/top_level.txt
lastfmapi_py-1.0.0.dist-info/RECORD
