Metadata-Version: 2.1
Name: lastfmapi-py
Version: 1.0.0
Summary: Get charts, top artists and top songs WITHOUT LastFM API
Home-page: https://github.com/mytja/lastfm-py
Author: mytja
Author-email: mytja@protonmail.com
License: MIT
Platform: UNKNOWN
Classifier: Programming Language :: Python :: 3
Classifier: License :: OSI Approved :: MIT License
Classifier: Operating System :: OS Independent
Requires-Python: >=3.6
License-File: LICENSE
Requires-Dist: httpx
